blueprint_client/__init__.py
blueprint_client/client.py
blueprint_client/const.py
blueprint_client-1.0.1.dist-info/LICENSE.md
blueprint_client-1.0.1.dist-info/METADATA
blueprint_client-1.0.1.dist-info/WHEEL
blueprint_client-1.0.1.dist-info/top_level.txt
blueprint_client-1.0.1.dist-info/RECORD
