Metadata-Version: 2.1
Name: blueprint-client
Version: 1.0.1
Summary: Constants.
Home-page: https://github.com/Limych/py-blueprint
Author: Andrey Khrolenok
Author-email: andrey@khrolenok.ru
License: MIT License
Platform: UNKNOWN
Classifier: Development Status :: 5 - Production/Stable
Classifier: Intended Audience :: Developers
Classifier: Programming Language :: Python :: 3
Classifier: License :: OSI Approved :: MIT License
Classifier: Operating System :: OS Independent
